<?xml version="1.0" encoding="utf-8"?>
<settings version="604">
   <groups type="bookmark">
      <group id="100">
         <setting key="title" runtime="true">***FeraLab*** Official</setting>
         <setting key="url" runtime="true">http://feralab.ru</setting>
      </group>
      <group id="101">
         <setting key="title" runtime="true">FeraLab Facebook</setting>
         <setting key="url" runtime="true">https://www.facebook.com/groups/267628853317794</setting>
      </group>
	  <group id="103">
         <setting key="title" runtime="true">FeraLab XDA</setting>
         <setting key="url" runtime="true">http://forum.xda-developers.com/showthread.php?t=1458001</setting>
      </group>
	  <group id="104">
         <setting key="title" runtime="true">FeraLab 4PDA</setting>
         <setting key="url" runtime="true">http://4pda.ru/forum/index.php?showtopic=337228&view=getnewpost</setting>
      </group>
      <group id="105">
         <setting key="title" runtime="true">FeraLab YouTube</setting>
         <setting key="url" runtime="true">http://www.youtube.com/user/FeraLab/videos</setting>
      </group>
   </groups>
</settings>